{
  "antoine-griezmann": {
    "title": "Antoine Griezmann : Une Carrière Légendaire et un Héritage en Bleu",
    "content": "Antoine Griezmann, l’un des attaquants les plus talentueux et influents du football français, a marqué de son empreinte l’histoire de l’Équipe de France et du football international. Après une carrière impressionnante couronnée de succès, son départ de la scène internationale laisse un grand vide, mais son héritage reste gravé dans la mémoire des fans et des générations futures.\n\n Débuts et Ascension\n\nGriezmann a fait ses débuts professionnels en 2009 à la Real Sociedad avant de rejoindre l'Atlético Madrid en 2014. C’est à Madrid que sa carrière a pris son envol, faisant de lui l'un des meilleurs joueurs au monde. Son flair pour le but, sa technique et son intelligence de jeu ont rapidement attiré l’attention des grands clubs et de l’Équipe de France.\n\n L'Aventure avec les Bleus\n\nAntoine Griezmann a débuté avec l'Équipe de France en 2014 et est rapidement devenu une pièce maîtresse de l'attaque française. Il a été un élément clé lors de l'Euro 2016, où il a remporté le Soulier d'Or en tant que meilleur buteur du tournoi. Mais c'est lors de la Coupe du Monde 2018 que Griezmann a véritablement gravé son nom dans l’histoire en aidant les Bleus à décrocher leur deuxième étoile. Sa performance en finale, avec un but et une passe décisive, restera un moment emblématique de sa carrière.\n\n Un Leader sur et en dehors du Terrain\n\nGriezmann n’était pas seulement un attaquant prolifique, il était aussi un leader sur le terrain. Sa capacité à motiver ses coéquipiers et à mener par l'exemple a été reconnue par ses entraîneurs et ses pairs. Il a toujours été un joueur d’équipe, sacrifiant souvent ses propres statistiques pour le bien collectif.\n\n La Retraite Internationale\n\nEn 2024, après plus de 10 ans sous le maillot bleu, Antoine Griezmann a annoncé sa retraite internationale. Avec plus de 120 sélections et plus de 40 buts, il laisse derrière lui une carrière internationale exceptionnelle. Sa décision de se retirer a été saluée par de nombreuses personnalités du football, reconnaissant son impact durable sur l’Équipe de France.\n\n L'Héritage de Griezmann\n\nAntoine Griezmann a contribué à redéfinir le rôle de l'attaquant moderne. Polyvalent, il pouvait jouer à plusieurs postes, alliant technique, intelligence de jeu et efficacité devant le but. Son héritage au sein de l'Équipe de France est immense, et il reste un modèle pour les jeunes générations qui rêvent de revêtir le maillot bleu.\n\nEn conclusion, Antoine Griezmann est une légende du football français. Son départ de la scène internationale marque la fin d'une ère, mais son influence continuera d’inspirer l'Équipe de France pendant de nombreuses années.",
    "image": "assets/images/blogs/antoine.avif",
    "description": "",
    "collection": "sports",
    "injectedImages": [
      {
        "src": "assets/images/blogs/injectedBlogsImages/creizmenn.avif",
        "line": 4,
        "position": "right"
      }
    ],
    "dateEcriture": "2024-10-01"
  },
  "Temps d'éducation pendant le Ramadan": {
    "title": "Temps d'éducation pendant le Ramadan",
    "content": "Le Ramadan est un mois sacré pour les musulmans, marqué par le jeûne, la prière, la charité et la réflexion spirituelle. En plus de son importance religieuse, c'est aussi un moment propice à l'éducation et à la transmission des valeurs fondamentales de l'Islam, telles que la patience, la solidarité et la gratitude. Pendant ce mois, les musulmans sont invités à se concentrer sur leur spiritualité en renforçant leur connexion avec Dieu, en recherchant la pureté intérieure et en adoptant des comportements plus respectueux et conscients. C'est une période idéale pour encourager les jeunes à s'instruire sur les principes éthiques et moraux de leur foi, à développer un sens de l'empathie envers les autres, et à comprendre l'importance du sacrifice et de l'autodiscipline dans leur vie quotidienne.\n\nPour les élèves du collège et du lycée, l'emploi du temps révisé est le suivant :\n\nDu lundi au jeudi :\n\nSéance du matin : 8h40 – 12h (avec de courtes pauses)\n\nSéance de l'après-midi : 12h30 – 15h50\n\nEmploi du temps spécial pour les vendredis Afin de permettre aux élèves d'assister à la prière du vendredi sans perturber leur programme académique, un emploi du temps séparé a été mis en place :\n\nSéance du matin : 8h30 – 11h50\n\nSéance de l'après-midi : 13h40 – 17h (avec les pauses habituelles)\n\nLe ministère a également précisé que la mise en œuvre de ces ajustements nécessitait de la flexibilité, en tenant compte des circonstances uniques de chaque établissement, notamment dans les zones nécessitant une plus grande adaptabilité des horaires.",
    "image": "assets/images/blogs/Ramadan.avif",
    "description": "",
    "collection": "Autre",
    "injectedImages": [
      {
        "src": "assets/images/blogs/injectedBlogsImages/Horaires scolaires_ramadan_bon.avif",
        "line": 2,
        "position": "right"
      }
    ],
    "dateEcriture": "2025-03-04"
  },
  "Cristiano Ronaldo": {
    "title": "Cristiano Ronaldo : la biographie et la carrière",
    "content": "Cristiano Ronaldo, dont le nom complet est Cristiano Ronaldo dos Santos Aveiro, est né le 5 février 1985 à Funchal, sur l'île de Madère, au Portugal. Il est largement reconnu comme l'un des plus grands footballeurs de l'histoire, rivalisant avec Lionel Messi. Ronaldo a marqué le football par son talent exceptionnel, son engagement et sa capacité à exceller à un niveau élevé pendant de nombreuses années.\n\nJeunesse et débuts\n\nRonaldo a grandi dans un environnement modeste et a commencé à jouer au football dès son enfance. Il a intégré le club local, Andorinha, où son père était intendant. À l'âge de 12 ans, il a quitté sa famille pour rejoindre le continent et entrer à l'académie du Sporting CP, l'un des clubs les plus renommés du Portugal. Ses performances remarquables avec les équipes de jeunes ont rapidement attiré l'attention des grands clubs européens.\n\nCarrière professionnelle:\n\n1. Sporting CP (2002-2003):\n\nRonaldo a fait ses débuts professionnels avec le Sporting CP en 2002. Son talent éclatant a été mis en lumière lors d'un match amical contre Manchester United, où il a surpassé la défense adverse. Sir Alex Ferguson, alors entraîneur de Manchester United, a été si impressionné qu'il a décidé de l'engager\n\n2. Manchester United (2003-2009):\n\nEn 2003, Ronaldo a rejoint Manchester United pour un montant d'environ 12 millions de livres sterling. Sous la direction de Ferguson, il s'est rapidement affirmé comme l'un des joueurs les plus captivants du football mondial. Avec United, il a remporté trois titres de Premier League, une Coupe d'Angleterre, deux Coupes de la Ligue, une Ligue des Champions et une Coupe du Monde des Clubs. En 2008, il a reçu son premier Ballon d'Or, récompensant le meilleur joueur du monde\n\n3. Real Madrid (2009-2018):\n\nEn 2009, Cristiano Ronaldo a été transféré au Real Madrid pour un montant record de 94 millions d'euros, devenant ainsi le joueur le plus cher de l'histoire à ce moment-là. Au sein du club madrilène, il a atteint des sommets inégalés, remportant quatre Ligues des Champions, deux titres de La Liga, deux Coupes du Roi et quatre Ballons d'Or supplémentaires. Il est devenu le meilleur buteur de l'histoire du club, surpassant des icônes telles que Raúl et Alfredo Di Stéfano.\n\n4. Juventus (2018-2021):\n\nEn 2018, Ronaldo a créé la surprise en rejoignant la Juventus pour un montant de 100 millions d'euros. Avec l'équipe italienne, il a décroché deux titres de Serie A tout en continuant à marquer des buts à un rythme remarquable. Bien qu'il n'ait pas réussi à remporter la Ligue des Champions avec la Juventus, il a su démontrer qu'il restait l'un des joueurs les plus redoutés sur la scène mondiale.\n\n5. Retour à Manchester United (2021-2022):\n\nEn août 2021, Ronaldo a effectué un retour émouvant à Manchester United. Malgré les difficultés rencontrées par le club, il a continué à inscrire des buts et à faire preuve de leadership sur le terrain.\n\n6. Al-Nassr (depuis 2023):\n\nEn janvier 2023, Ronaldo a signé avec le club saoudien Al-Nassr, marquant ainsi un nouveau tournant dans sa carrière. Ce transfert a suscité un grand intérêt médiatique, car il a choisi de poursuivre sa carrière en Arabie Saoudite.\n\nCarrière internationale:\n\nRonaldo est également une figure emblématique de l'équipe nationale portugaise. Il est le meilleur buteur de l'histoire de la sélection et a participé à de nombreuses Coupes du Monde et Championnats d'Europe. Il a conduit le Portugal à la victoire lors de l'Euro 2016 et de la Ligue des Nations en 2019, deux titres prestigieux pour son pays.\n\nVie personnelle et influence:\n\nEn dehors du terrain, Ronaldo se distingue par son engagement philanthropique, ayant réalisé des contributions significatives à diverses œuvres caritatives. Il est également une figure emblématique à l'échelle mondiale, comptant des millions d'abonnés sur les réseaux sociaux et établissant des partenariats publicitaires avec des marques renommées telles que Nike, Herbalife et Clear.\n\nHéritage:\n\nCristiano Ronaldo incarne la détermination, le dévouement et le professionnalisme. Son héritage dans le domaine du football est incontestable et continuera d'inspirer les générations à venir. Que ce soit à travers ses réalisations spectaculaires, ses nombreux titres ou son impact mondial, Ronaldo demeurera à jamais une icône du sport.",
    "image": "assets/images/blogs/cristiano-ronaldo-al-nassr.avif",
    "description": "",
    "collection": "sports",
    "injectedImages": [
      {
        "src": "assets/images/blogs/injectedBlogsImages/ronaldo_man_united.avif",
        "line": 4,
        "position": "right"
      },
      {
        "src": "assets/images/blogs/injectedBlogsImages/ronaldo_RM.avif",
        "line": 17,
        "position": "right"
      },
      {
        "src": "assets/images/blogs/injectedBlogsImages/ronaldo_ph2.avif",
        "line": 32,
        "position": "right"
      }
    ],
    "dateEcriture": "2025-03-04"
  },
  "devops": {
    "title": "L’Essentiel du DevOps : Principes, Avantages et Défis",
    "content": "DevOps est une approche de développement logiciel qui vise à unifier le développement et les opérations afin d'améliorer la collaboration, l'efficacité et la qualité des livrables. En intégrant les pratiques et les outils de DevOps, les équipes peuvent automatiser les processus, accélérer les déploiements et répondre plus rapidement aux besoins des utilisateurs.\n\n Principes du DevOps\n\n1. Collaboration et Communication :\n   DevOps encourage une culture de collaboration entre les équipes de développement et d'opérations. En favorisant une communication ouverte et une coopération étroite, les équipes peuvent résoudre les problèmes plus efficacement et aligner leurs objectifs.\n\n2. Automatisation :\n   L'automatisation des processus de développement, de test, et de déploiement est un pilier central du DevOps. En automatisant les tâches répétitives et les workflows, les équipes peuvent réduire les erreurs humaines, accélérer les cycles de livraison et améliorer la cohérence des déploiements.\n\n3. Intégration Continue et Déploiement Continu (CI/CD) :\n   Les pratiques CI/CD visent à intégrer les modifications de code dans un dépôt central de manière continue et à déployer ces modifications automatiquement dans des environnements de production. Cela permet de détecter les problèmes plus tôt et de livrer de nouvelles fonctionnalités plus rapidement.\n\n4. Surveillance et Retour d'Information :\n   La surveillance des systèmes en production et la collecte de retours d'information sont essentielles pour identifier et résoudre les problèmes rapidement. Les outils de monitoring permettent d’assurer la disponibilité et les performances des applications, tout en fournissant des insights pour des améliorations continues.\n\n Avantages du DevOps\n\n1. Réduction du Temps de Mise sur le Marché :\n   En automatisant les processus et en favorisant des pratiques de développement efficaces, DevOps permet de livrer des produits plus rapidement. Cela réduit le temps de mise sur le marché et permet de répondre plus vite aux besoins des clients.\n\n2. Amélioration de la Qualité :\n   Les pratiques DevOps, telles que les tests automatisés et l’intégration continue, contribuent à améliorer la qualité du code. Les erreurs sont détectées plus tôt, et les équipes peuvent livrer des produits plus stables et fiables.\n\n3. Flexibilité et Agilité :\n   DevOps favorise une approche agile du développement, permettant aux équipes de s'adapter rapidement aux changements de besoins et aux nouvelles opportunités. Cela améliore la capacité à innover et à réagir aux évolutions du marché.\n\n4. Satisfaction Accrue des Clients :\n   En livrant des mises à jour plus fréquentes et en répondant plus efficacement aux problèmes, les équipes DevOps améliorent l’expérience utilisateur et la satisfaction des clients. Une meilleure qualité de service se traduit par une fidélisation accrue.\n\n Défis du DevOps\n\n1. Complexité de l’Implémentation :\n   La mise en œuvre de DevOps peut être complexe et nécessiter des changements importants dans les processus et les outils existants. Il est crucial d’avoir une stratégie claire et de gérer les aspects organisationnels et culturels du changement.\n\n2. Gestion du Changement :\n   Adopter DevOps implique souvent de modifier les rôles, les responsabilités et la culture d'entreprise. Gérer cette transition et obtenir l’adhésion de toutes les parties prenantes est un défi majeur.\n\n3. Intégration des Outils :\n   Le choix et l’intégration des outils DevOps peuvent être difficiles, en raison de la diversité des solutions disponibles et de la nécessité d'assurer leur compatibilité avec les systèmes existants.\n\n4. Sécurité :\n   En automatisant les processus et en intégrant des outils de déploiement, il est crucial de maintenir des pratiques de sécurité rigoureuses pour protéger les systèmes et les données. La sécurité doit être intégrée dans toutes les étapes du cycle de vie du développement.\n\nEn conclusion, DevOps offre une approche puissante pour améliorer la collaboration, l'efficacité et la qualité des processus de développement logiciel. En adoptant les principes de DevOps, les équipes peuvent accélérer les cycles de livraison, répondre aux besoins des clients et obtenir un avantage concurrentiel significatif.",
    "image": "assets/images/blogs/DevOps.avif",
    "description": "",
    "collection": "dev",
    "injectedImages": [
      {
        "src": "assets/images/blogs/injectedBlogsImages/devops1.avif",
        "line": 4,
        "position": "right"
      },
      {
        "src": "assets/images/blogs/injectedBlogsImages/devops2.avif",
        "line": 19,
        "position": "left"
      }
    ],
    "dateEcriture": "2024-09-10"
  },

  "abdelaziz_berrada": {
    "title": "Abdelaziz Berrada : Une Légende du Football Marocain",
    "content": "Abdelaziz Berrada est une figure emblématique du football marocain , connu pour son talent exceptionnel, son engagement et son influence durable sur le sport national. Né à Casablanca, Berrada a débuté sa carrière dans les clubs locaux avant de se hisser au rang de joueur international. En tant que milieu de terrain, il a captivé les fans par son jeu technique et stratégique, devenant rapidement un pilier pour son équipe et une source d'inspiration pour les jeunes talents marocains.\n\nUn Parcours Prometteur et Inspirant\n\n1. Début de Carrière :\n   Dès son plus jeune âge, Berrada a montré des aptitudes remarquables pour le football. Son passage par les centres de formation lui a permis de se démarquer et d'attirer l'attention des recruteurs. Il a su s’adapter rapidement, progressant de manière fulgurante et affirmant sa place parmi les jeunes joueurs prometteurs du Maroc.\n\n2. Ascension en Équipe Nationale :\n   La sélection de Berrada en équipe nationale a marqué un tournant décisif dans sa carrière. Il a su exploiter cette opportunité pour démontrer sa capacité à performer sous pression et à gérer les attentes élevées des supporters marocains. Sa détermination et son esprit d'équipe ont été des éléments clés qui ont renforcé la dynamique de l’équipe, faisant de lui un joueur essentiel lors des compétitions internationales.\n\n3. Style de Jeu et Technique :\n   Ce qui distingue Abdelaziz Berrada, c'est son style de jeu unique. En tant que milieu de terrain, il combine une vision de jeu impressionnante avec une précision technique rare. Sa capacité à anticiper les mouvements adverses et à distribuer des passes décisives a fait de lui un joueur redouté par ses adversaires. Berrada est aussi connu pour son travail acharné, son engagement sans faille, et sa capacité à se sacrifier pour le bien de l'équipe.\n\n4. Contributions en Club et en Sélection :\n   Au niveau des clubs, Berrada a joué un rôle central dans les équipes pour lesquelles il a évolué, contribuant à de nombreuses victoires et soulevant des trophées importants. En sélection, il a porté fièrement les couleurs du Maroc, laissant une empreinte durable sur le terrain. Sa présence a renforcé l’esprit d’équipe et inspiré de nombreux jeunes marocains qui rêvent de représenter leur pays un jour.\n\nUn Héritage Durable et une Source d'Inspiration\n\nAbdelaziz Berrada ne se limite pas à être un simple joueur de football. Son impact va bien au-delà des terrains. Il est devenu un véritable modèle pour les jeunes générations, incarnant des valeurs de discipline, de persévérance et de passion. Son engagement envers le sport a contribué à inspirer de nombreux jeunes à suivre leurs rêves et à travailler dur pour atteindre leurs objectifs.\n\nBerrada a également participé activement à des projets visant à promouvoir le football au Maroc. Il s’implique dans des initiatives de formation pour les jeunes et soutient des programmes qui offrent des opportunités aux talents en herbe, contribuant ainsi à renforcer le développement du football dans le pays.\n\nConclusion\n\nAbdelaziz Berrada restera sans aucun doute une légende du football marocain. Son parcours témoigne de l'importance de l'engagement et de la passion dans la réussite sportive. Que ce soit sur le terrain ou en dehors, Berrada incarne les valeurs du sport et inspire ceux qui le suivent. Sa contribution au football marocain continuera de marquer les esprits et de motiver les jeunes talents à viser toujours plus haut.",
    "image": "assets/images/blogs/berrada1.avif",
    "description": "",
    "collection": "sports",
    "injectedImages": [
      {
        "src": "assets/images/blogs/injectedBlogsImages/berrada2.avif",
        "line": 4,
        "position": "right"
      }
    ],
    "dateEcriture": "2024-10-25"
  },
  "ecommerce": {
    "title": "L'Essentiel des Sites Web et des Boutiques en Ligne pour le E-commerce",
    "content": "Dans l'ère numérique d'aujourd'hui, avoir un site web ou une boutique en ligne est essentiel pour réussir dans le commerce électronique. Ces plateformes permettent aux entreprises de toucher un large public, de vendre leurs produits et services 24/7, et de créer des expériences personnalisées pour leurs clients.\n\n Principes du E-commerce en ligne\n\n1. Accessibilité et Présence Globale :\n   Un site web bien conçu permet aux entreprises de se faire connaître à l'échelle mondiale, atteignant ainsi des clients potentiels dans n'importe quelle région. Contrairement aux magasins physiques, un site e-commerce est disponible à toute heure, ce qui augmente considérablement les opportunités de vente.\n\n2. Expérience Utilisateur (UX) :\n   L'expérience utilisateur est cruciale pour le succès d'un site e-commerce. Un site facile à naviguer, rapide, et sécurisé incite les visiteurs à acheter. L'UX englobe l'interface utilisateur (UI), la fluidité des transactions et la présentation des produits.\n\n3. Mobile et Responsive Design :\n   Avec la montée en puissance des smartphones, il est essentiel que les boutiques en ligne soient adaptées aux appareils mobiles. Un design responsive garantit que le site s'affiche correctement et offre une bonne expérience de navigation, quel que soit le type d'appareil.\n\n4. Sécurité et Confiance :\n   La sécurité des transactions en ligne est primordiale pour instaurer la confiance. Des solutions de paiement sécurisées, un certificat SSL et une gestion efficace des données personnelles sont des éléments clés pour garantir la protection des informations des clients.\n\n Avantages du E-commerce en ligne\n\n1. Accessibilité 24/7 :\n   Un site e-commerce permet aux entreprises de vendre à toute heure, permettant aux clients d'acheter quand ils le souhaitent, ce qui augmente les ventes et améliore la satisfaction client.\n\n2. Réduction des Coûts Opérationnels :\n   Contrairement aux magasins physiques, les coûts associés à un site web sont souvent plus faibles. Il n'y a pas de frais liés aux loyers ou aux équipes de vente en magasin, ce qui permet de réaliser des économies substantielles.\n\n3. Personnalisation et Marketing Ciblé :\n   Les boutiques en ligne peuvent utiliser des outils d'analyse pour comprendre le comportement des utilisateurs et offrir des recommandations personnalisées. De plus, des campagnes de marketing par e-mail et des publicités ciblées peuvent améliorer l'engagement des clients et stimuler les ventes.\n\n4. Gestion des Stocks et Logistique :\n   Les sites e-commerce permettent une gestion plus efficace des stocks, avec des systèmes de suivi automatisés et la possibilité d'intégrer des solutions logistiques pour expédier rapidement les produits.\n\n Défis du E-commerce en ligne\n\n1. Concurrence Intense :\n   Avec la croissance rapide du commerce en ligne, la concurrence est féroce. Se démarquer nécessite une stratégie de marketing solide, une excellente expérience utilisateur et une proposition de valeur unique.\n\n2. Gestion des Retours et de la Logistique :\n   La gestion des retours de produits et la logistique peuvent être complexes. Les entreprises doivent s'assurer que le processus de retour est facile pour les clients tout en minimisant les coûts liés à l'expédition et au traitement des retours.\n\n3. Dépendance Technologique :\n   Un site e-commerce repose fortement sur la technologie. Les pannes techniques, les cyberattaques ou les problèmes de performance peuvent affecter les ventes et la réputation de l'entreprise.\n\n4. Acquisition et Fidélisation des Clients :\n   Attirer des visiteurs sur un site e-commerce est un défi. Il est essentiel de mettre en place des stratégies de référencement (SEO), de publicité en ligne, et de fidélisation pour convertir les visiteurs en clients réguliers.\n\nEn conclusion, un site web ou une boutique en ligne est un élément fondamental du commerce électronique. Il permet aux entreprises de se connecter avec une audience mondiale, de vendre à toute heure, et d'offrir une expérience client enrichissante. Cependant, pour réussir, il est crucial de veiller à une excellente conception, une gestion efficace et une stratégie marketing adaptée.",
    "image": "assets/images/blogs/ecommerce.avif",
    "description": "L'importance des sites web et des boutiques en ligne pour le commerce électronique.",
    "collection": "ecommerce",
    "injectedImages": [
      {
        "src": "assets/images/blogs/injectedBlogsImages/ecommerce1.avif",
        "line": 5,
        "position": "right"
      },
      {
        "src": "assets/images/blogs/injectedBlogsImages/ecommerce2.avif",
        "line": 20,
        "position": "left"
      }
    ],
    "dateEcriture": "2024-11-27"
  },

  "gitex-africa": {
    "title": "GITEX AFRICA 2025 : Le Rendez-vous Incontournable des Leaders Technologiques du Continent",

    "content": "Le GITEX AFRICA, salon phare de l'innovation technologique sur le continent africain, s'apprête à ouvrir ses portes pour une édition 2025 qui s'annonce révolutionnaire. Après le succès retentissant des éditions précédentes, cet événement s'est imposé comme le carrefour incontournable pour les entrepreneurs, investisseurs et experts tech de toute l'Afrique et au-delà.\n\n<h2 style=\"color: #258F95; border-bottom: 2px solid #258F95; padding-bottom: 5px;\">Un épicentre d'innovation et d'opportunités d'affaires</h2>\nLe GITEX AFRICA n'est pas simplement un salon technologique , c'est une véritable plateforme d'accélération pour l'écosystème digital africain. Avec plus de 1000 exposants attendus, représentant plus de 100 pays, l'événement se positionne comme un catalyseur essentiel pour le développement technologique du continent.Les secteurs représentés couvriront un large spectre : intelligence artificielle et robotique, Smart cities et infrastructures numériques, fintech et solutions de paiement innovantes, cybersécurité et protection des données, agritech et solutions durables et e-commerce et marketplaces.\n\n<h2 style=\"color: #258F95; border-bottom: 2px solid #258F95; padding-bottom: 5px;\">Des conférenciers de renom à l'affiche</h2>\nCette édition accueillera des intervenants de classe mondiale, parmi lesquels des CEO de licornes africaines, des ministres du numérique de plusieurs pays et des experts internationaux. Les sessions plénières et ateliers aborderont les problématiques cruciales pour l'avenir digital du continent : souveraineté numérique, inclusion financière, formation aux compétences de demain et financement de l'innovation.\n\n<h2 style=\"color: #258F95; border-bottom: 2px solid #258F95; padding-bottom: 5px;\">Opportunité exclusive pour nos lecteurs : codes promotionnels</h2>\nPour cette édition 2025, nous sommes heureux de vous proposer des codes promotionnels exclusifs pour accéder à l'événement. Plusieurs options sont disponibles selon vos besoins :\n\n<div style=\"background-color: #f0f5f5; padding: 15px; border-radius: 6px; margin: 15px 0; box-shadow: 0 2px 5px rgba(37, 143, 149, 0.1);\">\n<strong style=\"color: #000; font-size: 16px; display: block; margin-bottom: 10px; border-bottom: 1px solid rgba(37, 143, 149, 0.2); padding-bottom: 5px;\">Réductions Premium (25% à 30%)</strong>\n<ul style=\"list-style-type: none; padding-left: 5px; margin: 0;\">\n<li style=\"margin-bottom: 8px; display: flex; align-items: center;\">\n  <span style=\"background-color: rgba(37, 143, 149, 0.15); color: #000; padding: 4px 8px; border-radius: 4px; font-family: monospace; font-weight: bold; margin-right: 10px; letter-spacing: 0.5px; display: inline-block; min-width: 110px; border-left: 3px solid #258F95;\">GAEO0EG4KM</span>\n  <span style=\"background-color: rgba(37, 143, 149, 0.2); color: #000; padding: 2px 8px; border-radius: 10px; font-weight: 600; margin-right: 10px;\">-30%</span>\n  <span style=\"color: #000; font-weight: 500;\">Pass Premium (accès à toutes les conférences)</span>\n</li>\n<li style=\"margin-bottom: 8px; display: flex; align-items: center;\">\n  <span style=\"background-color: rgba(37, 143, 149, 0.15); color: #000; padding: 4px 8px; border-radius: 4px; font-family: monospace; font-weight: bold; margin-right: 10px; letter-spacing: 0.5px; display: inline-block; min-width: 110px; border-left: 3px solid #258F95;\">Vis4QNQZL1</span>\n  <span style=\"background-color: rgba(37, 143, 149, 0.2); color: #000; padding: 2px 8px; border-radius: 10px; font-weight: 600; margin-right: 10px;\">-30%</span>\n  <span style=\"color: #000; font-weight: 500;\">Pass Premium (accès à toutes les conférences)</span>\n</li>\n<li style=\"margin-bottom: 8px; display: flex; align-items: center;\">\n  <span style=\"background-color: rgba(37, 143, 149, 0.15); color: #000; padding: 4px 8px; border-radius: 4px; font-family: monospace; font-weight: bold; margin-right: 10px; letter-spacing: 0.5px; display: inline-block; min-width: 110px; border-left: 3px solid #258F95;\">TECH25PREM</span>\n  <span style=\"background-color: rgba(37, 143, 149, 0.2); color: #000; padding: 2px 8px; border-radius: 10px; font-weight: 600; margin-right: 10px;\">-25%</span>\n  <span style=\"color: #000; font-weight: 500;\">Pass Premium (accès à toutes les conférences)</span>\n</li>\n</ul>\n</div>\n\n<div style=\"background-color: #f0f5f5; padding: 15px; border-radius: 6px; margin: 15px 0; box-shadow: 0 2px 5px rgba(37, 143, 149, 0.1);\">\n<strong style=\"color: #000; font-size: 16px; display: block; margin-bottom: 10px; border-bottom: 1px solid rgba(37, 143, 149, 0.2); padding-bottom: 5px;\">Réductions Pro et Standard (15% à 20%)</strong>\n<ul style=\"list-style-type: none; padding-left: 5px; margin: 0;\">\n<li style=\"margin-bottom: 8px; display: flex; align-items: center;\">\n  <span style=\"background-color: rgba(37, 143, 149, 0.15); color: #000; padding: 4px 8px; border-radius: 4px; font-family: monospace; font-weight: bold; margin-right: 10px; letter-spacing: 0.5px; display: inline-block; min-width: 110px; border-left: 3px solid #258F95;\">AFRIC20PRO</span>\n  <span style=\"background-color: rgba(37, 143, 149, 0.2); color: #000; padding: 2px 8px; border-radius: 10px; font-weight: 600; margin-right: 10px;\">-20%</span>\n  <span style=\"color: #000; font-weight: 500;\">Pass Pro (accès conférences + ateliers)</span>\n</li>\n<li style=\"margin-bottom: 8px; display: flex; align-items: center;\">\n  <span style=\"background-color: rgba(37, 143, 149, 0.15); color: #000; padding: 4px 8px; border-radius: 4px; font-family: monospace; font-weight: bold; margin-right: 10px; letter-spacing: 0.5px; display: inline-block; min-width: 110px; border-left: 3px solid #258F95;\">EARLYJ15PS</span>\n  <span style=\"background-color: rgba(37, 143, 149, 0.2); color: #000; padding: 2px 8px; border-radius: 10px; font-weight: 600; margin-right: 10px;\">-15%</span>\n  <span style=\"color: #000; font-weight: 500;\">Pass Standard (journée complète)</span>\n</li>\n</ul>\n</div>\n\n<div style=\"background-color: #f0f5f5; padding: 15px; border-radius: 6px; margin: 15px 0; box-shadow: 0 2px 5px rgba(37, 143, 149, 0.1);\">\n<strong style=\"color: #000; font-size: 16px; display: block; margin-bottom: 10px; border-bottom: 1px solid rgba(37, 143, 149, 0.2); padding-bottom: 5px;\">Pass Gratuits (100%)</strong>\n<ul style=\"list-style-type: none; padding-left: 5px; margin: 0;\">\n<li style=\"margin-bottom: 8px; display: flex; align-items: center;\">\n  <span style=\"background-color: rgba(37, 143, 149, 0.15); color: #000; padding: 4px 8px; border-radius: 4px; font-family: monospace; font-weight: bold; margin-right: 10px; letter-spacing: 0.5px; display: inline-block; min-width: 110px; border-left: 3px solid #258F95;\">AFR7TEC9ZX</span>\n  <span style=\"background-color: rgba(37, 143, 149, 0.2); color: #000; padding: 2px 8px; border-radius: 10px; font-weight: 600; margin-right: 10px;\">100%</span>\n  <span style=\"color: #000; font-weight: 500;\">Pass Visitor (entrée gratuite)</span>\n</li>\n<li style=\"margin-bottom: 8px; display: flex; align-items: center;\">\n  <span style=\"background-color: rgba(37, 143, 149, 0.15); color: #000; padding: 4px 8px; border-radius: 4px; font-family: monospace; font-weight: bold; margin-right: 10px; letter-spacing: 0.5px; display: inline-block; min-width: 110px; border-left: 3px solid #258F95;\">INNOV25KDQ</span>\n  <span style=\"background-color: rgba(37, 143, 149, 0.2); color: #000; padding: 2px 8px; border-radius: 10px; font-weight: 600; margin-right: 10px;\">100%</span>\n  <span style=\"color: #000; font-weight: 500;\">Pass Visitor (entrée gratuite)</span>\n</li>\n<li style=\"margin-bottom: 8px; display: flex; align-items: center;\">\n  <span style=\"background-color: rgba(37, 143, 149, 0.15); color: #000; padding: 4px 8px; border-radius: 4px; font-family: monospace; font-weight: bold; margin-right: 10px; letter-spacing: 0.5px; display: inline-block; min-width: 110px; border-left: 3px solid #258F95;\">DIGIT8LM3P</span>\n  <span style=\"background-color: rgba(37, 143, 149, 0.2); color: #000; padding: 2px 8px; border-radius: 10px; font-weight: 600; margin-right: 10px;\">100%</span>\n  <span style=\"color: #000; font-weight: 500;\">Pass Visitor (entrée gratuite)</span>\n</li>\n<li style=\"margin-bottom: 8px; display: flex; align-items: center;\">\n  <span style=\"background-color: rgba(37, 143, 149, 0.15); color: #000; padding: 4px 8px; border-radius: 4px; font-family: monospace; font-weight: bold; margin-right: 10px; letter-spacing: 0.5px; display: inline-block; min-width: 110px; border-left: 3px solid #258F95;\">STRTUP2025</span>\n  <span style=\"background-color: rgba(37, 143, 149, 0.2); color: #000; padding: 2px 8px; border-radius: 10px; font-weight: 600; margin-right: 10px;\">100%</span>\n  <span style=\"color: #000; font-weight: 500;\">Pass Startup (espace exposants + networking)</span>\n</li>\n<li style=\"margin-bottom: 0; display: flex; align-items: center;\">\n  <span style=\"background-color: rgba(37, 143, 149, 0.15); color: #000; padding: 4px 8px; border-radius: 4px; font-family: monospace; font-weight: bold; margin-right: 10px; letter-spacing: 0.5px; display: inline-block; min-width: 110px; border-left: 3px solid #258F95;\">ETUDIA25FR</span>\n  <span style=\"background-color: rgba(37, 143, 149, 0.2); color: #000; padding: 2px 8px; border-radius: 10px; font-weight: 600; margin-right: 10px;\">100%</span>\n  <span style=\"color: #000; font-weight: 500;\">Pass Étudiant (sur présentation d'un justificatif)</span>\n</li>\n</ul>\n</div>\n\n<p style=\"font-size: 14px; color: #555; text-align: center; font-style: italic; margin: 10px 0 20px; background-color: rgba(37, 143, 149, 0.05); padding: 8px; border-radius: 4px;\">Ces codes sont valables jusqu'à 3 jours avant l'événement dans la limite des places disponibles.</p>\n\n<h2 style=\"color: #258F95; border-bottom: 2px solid #258F95; padding-bottom: 5px;\">La transformation digitale africaine en pleine accélération</h2>\nLe GITEX AFRICA 2025 intervient dans un contexte particulièrement favorable pour la tech africaine. Selon les dernières études sectorielles, les investissements dans les startups africaines ont dépassé les <span style=\"color: #258F95; font-weight: bold;\">8 milliards de dollars en 2024</span>, avec une croissance annuelle de <span style=\"color: #258F95; font-weight: bold;\">22%</span> malgré les tensions économiques mondiales.\n\nL'émergence de hubs technologiques dans plusieurs régions du continent témoigne de cette dynamique : au-delà des pôles traditionnels comme Lagos, Le Cap ou Nairobi, de nouveaux écosystèmes florissants se développent à Kigali, Dakar, Tunis et Casablanca.\n\n<h2 style=\"color: #258F95; border-bottom: 2px solid #258F95; padding-bottom: 5px;\">Cinq tendances majeures à surveiller lors du GITEX AFRICA 2025</h2>\n<ol style=\"padding-left: 20px;\">\n<li><strong style=\"color: #258F95;\">L'IA au service du développement local</strong> : Les solutions d'intelligence artificielle adaptées aux besoins spécifiques africains seront particulièrement mises en avant. Des applications dans les domaines de la santé, de l'agriculture et de l'éducation démontreront comment l'IA peut contribuer à relever les défis socio-économiques du continent.</li>\n<li><strong style=\"color: #258F95;\">L'explosion des infrastructures 5G</strong> : Le déploiement accéléré des réseaux 5G à travers le continent ouvre la voie à une nouvelle génération de services numériques. Les opérateurs télécoms présenteront leurs feuilles de route et des cas d'usage innovants pour cette technologie transformative.</li>\n<li><strong style=\"color: #258F95;\">La révolution du paiement mobile 2.0</strong> : L'Afrique, pionnière dans l'adoption du mobile money, entre dans une nouvelle phase avec des solutions de paiement encore plus intégrées. Interopérabilité transfrontalière, services financiers élargis et inclusion des populations non bancarisées seront au cœur des discussions.</li>\n<li><strong style=\"color: #258F95;\">Le cloud souverain africain</strong> : La question de la souveraineté des données devient centrale pour les gouvernements et entreprises du continent. Plusieurs initiatives de cloud souverain africain seront présentées, visant à garantir que les données des citoyens et organisations africaines soient hébergées localement.</li>\n<li><strong style=\"color: #258F95;\">L'économie circulaire numérique</strong> : Face aux défis environnementaux, les solutions technologiques favorisant l'économie circulaire gagneront en visibilité. Recyclage des équipements électroniques, optimisation énergétique des data centers et conception durable seront à l'honneur.</li>\n</ol>\n\n<h2 style=\"color: #258F95; border-bottom: 2px solid #258F95; padding-bottom: 5px;\">Plan interactif du salon</h2>\nPour vous aider à naviguer efficacement dans cet événement d'envergure, nous vous invitons à explorer la carte interactive officielle du GITEX AFRICA 2025 ci-dessous :\n\n<div style=\"width: 100%; height: 400px; margin: 20px 0; border-radius: 8px; overflow: hidden; box-shadow: 0 4px 12px rgba(37, 143, 149, 0.2); border: 1px solid rgba(37, 143, 149, 0.1);\">\n<iframe src=\"https://map.gitexafrica.com/?mapId=9AyWG4q5gYrlJ\" style=\"width: 100%; height: 100%; border: none;\" allowfullscreen></iframe>\n</div>\n\n<hr style=\"height: 3px; background: linear-gradient(to right, #258F95, rgba(37, 143, 149, 0.1)); border: none; margin: 40px 0 30px;\"/>\n\n<div style=\"margin-bottom: 30px;\">\n  <h3 style=\"color: #258F95; font-size: 20px; margin-bottom: 15px;\">Tags</h3>\n  \n  <div style=\"display: flex; flex-wrap: wrap; gap: 10px; margin-bottom: 20px;\">\n    <strong style=\"display: inline-block; padding: 6px 12px; background-color: #f0f5f5; border-radius: 4px; color: #258F95; font-size: 14px; border: 1px solid rgba(37, 143, 149, 0.2);\">GITEX Africa</strong>\n    <strong style=\"display: inline-block; padding: 6px 12px; background-color: #f0f5f5; border-radius: 4px; color: #258F95; font-size: 14px; border: 1px solid rgba(37, 143, 149, 0.2);\">GITEX Maroc</strong>\n    <strong style=\"display: inline-block; padding: 6px 12px; background-color: #f0f5f5; border-radius: 4px; color: #258F95; font-size: 14px; border: 1px solid rgba(37, 143, 149, 0.2);\">GITEX Marrakech</strong>\n    <strong style=\"display: inline-block; padding: 6px 12px; background-color: #f0f5f5; border-radius: 4px; color: #258F95; font-size: 14px; border: 1px solid rgba(37, 143, 149, 0.2);\">Code promo GITEX</strong>\n    <strong style=\"display: inline-block; padding: 6px 12px; background-color: #f0f5f5; border-radius: 4px; color: #258F95; font-size: 14px; border: 1px solid rgba(37, 143, 149, 0.2);\">Réductions GITEX</strong>\n    <strong style=\"display: inline-block; padding: 6px 12px; background-color: #f0f5f5; border-radius: 4px; color: #258F95; font-size: 14px; border: 1px solid rgba(37, 143, 149, 0.2);\">Pass gratuit GITEX</strong>\n    <strong style=\"display: inline-block; padding: 6px 12px; background-color: #f0f5f5; border-radius: 4px; color: #258F95; font-size: 14px; border: 1px solid rgba(37, 143, 149, 0.2);\">Tech Maroc</strong>\n    <strong style=\"display: inline-block; padding: 6px 12px; background-color: #f0f5f5; border-radius: 4px; color: #258F95; font-size: 14px; border: 1px solid rgba(37, 143, 149, 0.2);\">Innovation africaine</strong>\n    <strong style=\"display: inline-block; padding: 6px 12px; background-color: #f0f5f5; border-radius: 4px; color: #258F95; font-size: 14px; border: 1px solid rgba(37, 143, 149, 0.2);\">Salon technologique Marrakech</strong>\n    <strong style=\"display: inline-block; padding: 6px 12px; background-color: #f0f5f5; border-radius: 4px; color: #258F95; font-size: 14px; border: 1px solid rgba(37, 143, 149, 0.2);\">IA Afrique</strong>\n    <strong style=\"display: inline-block; padding: 6px 12px; background-color: #f0f5f5; border-radius: 4px; color: #258F95; font-size: 14px; border: 1px solid rgba(37, 143, 149, 0.2);\">5G Afrique</strong>\n    <strong style=\"display: inline-block; padding: 6px 12px; background-color: #f0f5f5; border-radius: 4px; color: #258F95; font-size: 14px; border: 1px solid rgba(37, 143, 149, 0.2);\">Fintech africaine</strong>\n    <strong style=\"display: inline-block; padding: 6px 12px; background-color: #f0f5f5; border-radius: 4px; color: #258F95; font-size: 14px; border: 1px solid rgba(37, 143, 149, 0.2);\">Cloud souverain</strong>\n    <strong style=\"display: inline-block; padding: 6px 12px; background-color: #f0f5f5; border-radius: 4px; color: #258F95; font-size: 14px; border: 1px solid rgba(37, 143, 149, 0.2);\">Économie circulaire numérique</strong>\n    <strong style=\"display: inline-block; padding: 6px 12px; background-color: #f0f5f5; border-radius: 4px; color: #258F95; font-size: 14px; border: 1px solid rgba(37, 143, 149, 0.2);\">Startup africaine</strong>\n    <strong style=\"display: inline-block; padding: 6px 12px; background-color: #f0f5f5; border-radius: 4px; color: #258F95; font-size: 14px; border: 1px solid rgba(37, 143, 149, 0.2);\">Événement tech 2025</strong>\n  </div>\n</div>\n\n<!-- 100 Hidden SEO Tags -->\n<div style=\"height: 0; overflow: hidden; position: absolute; visibility: hidden; width: 0;\">\n  <span>gitex afrique</span>\n  <span>salon tech maroc</span>\n  <span>gitex 2025</span>\n  <span>marrakech événement technologique</span>\n  <span>code reduction gitex africa</span>\n  <span>pass gratuit gitex</span>\n  <span>salon innovation maroc</span>\n  <span>gitex promotion code</span>\n  <span>événement intelligence artificielle afrique</span>\n  <span>exposition tech marrakech</span>\n  <span>conférence technologie afrique</span>\n  <span>code promo gitex marrakech</span>\n  <span>salon digital maroc</span>\n  <span>réduction billet gitex africa</span>\n  <span>technologie africaine innovation</span>\n  <span>gitex africa marrakech 2025</span>\n  <span>entrée gratuite salon technologique maroc</span>\n  <span>exposition innovation afrique</span>\n  <span>développement technologique africain</span>\n  <span>leader tech afrique</span>\n  <span>innovation numérique maroc</span>\n  <span>gitex africa codes promotionnels</span>\n  <span>plateforme technologique africaine</span>\n  <span>marrakech tech hub</span>\n  <span>salon professionnel technologie maroc</span>\n  <span>intelligence artificielle afrique</span>\n  <span>écosystème numérique africain</span>\n  <span>infrastructure technologique afrique</span>\n  <span>conference tech maroc</span>\n  <span>solutions intelligentes afrique</span>\n  <span>événement tech 2025 maroc</span>\n  <span>fintech maroc salon</span>\n  <span>transformations numériques afrique</span>\n  <span>gitex africa remise</span>\n  <span>salon innovation digitale maroc</span>\n  <span>code reduction gitex</span>\n  <span>startups africaines tech</span>\n  <span>événement numérique marrakech</span>\n  <span>technologies émergentes afrique</span>\n  <span>salon professionnel numérique</span>\n  <span>afrique transformation digitale</span>\n  <span>maroc hub technologique</span>\n  <span>conférence innovation marrakech</span>\n  <span>technologies 5g afrique</span>\n  <span>billet gratuit salon tech</span>\n  <span>salon technologie information maroc</span>\n  <span>événement blockchain afrique</span>\n  <span>fintech solutions africaines</span>\n  <span>réduction entrée gitex africa</span>\n  <span>entrepreneurs tech africains</span>\n  <span>smart cities afrique salon</span>\n  <span>cybersécurité afrique event</span>\n  <span>salon tech professionnels maroc</span>\n  <span>agritech solutions afrique</span>\n  <span>économie numérique africaine</span>\n  <span>cloud computing afrique salon</span>\n  <span>investissement tech afrique</span>\n  <span>salon e-commerce maroc</span>\n  <span>technologies disruptives afrique</span>\n  <span>innovation hub marrakech</span>\n  <span>événement robotique afrique</span>\n  <span>solutions paiement mobile afrique</span>\n  <span>internet des objets afrique salon</span>\n  <span>leaders technologiques africains</span>\n  <span>développement durable technologies afrique</span>\n  <span>évènement tech professionnels maroc</span>\n  <span>networking tech afrique</span>\n  <span>innovations technologiques africaines</span>\n  <span>smart solutions afrique</span>\n  <span>inclusion numérique afrique</span>\n  <span>gitex africa billets</span>\n  <span>technologies éducatives afrique</span>\n  <span>forum tech maroc</span>\n  <span>événement tech continental afrique</span>\n  <span>transformation numérique maroc</span>\n  <span>souveraineté numérique afrique</span>\n  <span>salon tech entreprises maroc</span>\n  <span>infrastructures digitales afrique</span>\n  <span>solutions e-health afrique</span>\n  <span>compétences numériques afrique</span>\n  <span>innovation tech marrakech</span>\n  <span>salon tech finance afrique</span>\n  <span>entreprises technologiques maroc</span>\n  <span>solutions tech durables afrique</span>\n  <span>digital growth afrique</span>\n  <span>économie circulaire numérique afrique</span>\n  <span>investisseurs tech afrique</span>\n  <span>réduction pass premium gitex</span>\n  <span>technologies santé afrique salon</span>\n  <span>optimisation énergétique data centers afrique</span>\n  <span>technologies vertes afrique</span>\n  <span>marketplaces africaines salon</span>\n  <span>financement innovation tech afrique</span>\n  <span>inclusion financière tech afrique</span>\n  <span>technologies éducation afrique</span>\n  <span>solutions protection données afrique</span>\n  <span>tech healthcare afrique</span>\n  <span>développeurs africains event</span>\n  <span>événement startupers maroc</span>\n  <span>réduction -30% gitex</span>\n  <span>pass visitor gitex africa 2025</span>\n  <span>GITEX Africa Marrakech inscription</span>\n  <span>pass premium GITEX Africa</span>\n  <span>promotion code salon technology</span>\n  <span>entrée salon technologique marrakech</span>\n</div>",

    "image": "assets/images/blogs/Gitex-africa.png",
    "description": "Découvrez tout ce qu'il faut savoir sur le GITEX AFRICA 2025, le plus grand salon technologique du continent africain, avec des codes promotionnels exclusifs et les dernières tendances tech.",
    "collection": "technologie",
    "injectedImages": [
      {
        "src": "assets/images/blogs/injectedBlogsImages/gitexAfrica.png",
        "line": 2,
        "position": "center"
      }
    ],
    "dateEcriture": "2025-04-08"
  },
  "SIEL": {
    "title": "SIEL 2025 : 30ème Salon International de l'Edition et du Livre de Rabat - Rendez-vous Incontournable des Amateurs de Littérature",

    "content": "Le Salon International de l'Edition et du Livre (SIEL) de Rabat célèbre sa 30ème édition, un événement culturel majeur qui réunit les passionnés de littérature, les éditeurs, les auteurs et les amoureux des livres de tout le Maroc et au-delà.\n\n<h2 style=\"color: #4A90E2; border-bottom: 2px solid #4A90E2; padding-bottom: 5px;\">Un Carrefour Culturel International</h2>\nLe SIEL n'est pas simplement un salon du livre, c'est une véritable plateforme d'échanges culturels et littéraires. Avec plus de 500 maisons d'édition attendues, représentant plus de 20 pays, l'événement se positionne comme un catalyseur essentiel pour le dialogue interculturel et la promotion de la lecture.\n\n<h2 style=\"color: #4A90E2; border-bottom: 2px solid #4A90E2; padding-bottom: 5px;\">Informations Pratiques</h2>\n<div style=\"background-color: #f0f7ff; padding: 15px; border-radius: 6px; margin: 15px 0; box-shadow: 0 2px 5px rgba(74, 144, 226, 0.1);\">\n<strong style=\"color: #000; font-size: 16px; display: block; margin-bottom: 10px; border-bottom: 1px solid rgba(74, 144, 226, 0.2); padding-bottom: 5px;\">Détails de l'Événement</strong>\n<ul style=\"list-style-type: none; padding-left: 5px; margin: 0;\">\n<li style=\"margin-bottom: 8px; display: flex; align-items: center;\">\n  <span style=\"background-color: rgba(74, 144, 226, 0.15); color: #000; padding: 4px 8px; border-radius: 4px; font-family: monospace; font-weight: bold; margin-right: 10px; letter-spacing: 0.5px; display: inline-block; min-width: 110px; border-left: 3px solid #4A90E2;\">📅 Dates</span>\n  <span style=\"color: #000; font-weight: 500;\">Du 18 au 27 Avril 2025</span>\n</li>\n<li style=\"margin-bottom: 8px; display: flex; align-items: center;\">\n  <span style=\"background-color: rgba(74, 144, 226, 0.15); color: #000; padding: 4px 8px; border-radius: 4px; font-family: monospace; font-weight: bold; margin-right: 10px; letter-spacing: 0.5px; display: inline-block; min-width: 110px; border-left: 3px solid #4A90E2;\">📍 Lieu</span>\n  <span style=\"color: #000; font-weight: 500;\">Rabat, Maroc</span>\n</li>\n<li style=\"margin-bottom: 8px; display: flex; align-items: center;\">\n  <span style=\"background-color: rgba(74, 144, 226, 0.15); color: #000; padding: 4px 8px; border-radius: 4px; font-family: monospace; font-weight: bold; margin-right: 10px; letter-spacing: 0.5px; display: inline-block; min-width: 110px; border-left: 3px solid #4A90E2;\">🎫 Billetterie</span>\n  <a href=\"https://billetteriesiel.minculture.gov.ma/tickets/salon-du-livre/4\" style=\"color: #4A90E2; text-decoration: none; font-weight: 600;\">Achat des billets en ligne</a>\n</li>\n</ul>\n</div>\n\n<h2 style=\"color: #4A90E2; border-bottom: 2px solid #4A90E2; padding-bottom: 5px;\">Redirections et Informations Complémentaires</h2>\n<div style=\"background-color: #f0f7ff; padding: 15px; border-radius: 6px; margin: 15px 0; box-shadow: 0 2px 5px rgba(74, 144, 226, 0.1);\">\n<strong style=\"color: #000; font-size: 16px; display: block; margin-bottom: 10px; border-bottom: 1px solid rgba(74, 144, 226, 0.2); padding-bottom: 5px;\">Liens Utiles</strong>\n<ul style=\"list-style-type: none; padding-left: 5px; margin: 0;\">\n<li style=\"margin-bottom: 8px; display: flex; align-items: center;\">\n  <span style=\"background-color: rgba(74, 144, 226, 0.15); color: #000; padding: 4px 8px; border-radius: 4px; font-family: monospace; font-weight: bold; margin-right: 10px; letter-spacing: 0.5px; display: inline-block; min-width: 110px; border-left: 3px solid #4A90E2;\">🌐 Site Officiel</span>\n  <a href=\"https://siel.ma/fr/accueil/\" style=\"color: #4A90E2; text-decoration: none; font-weight: 600;\">siel.ma</a>\n</li>\n<li style=\"margin-bottom: 8px; display: flex; align-items: center;\">\n  <span style=\"background-color: rgba(74, 144, 226, 0.15); color: #000; padding: 4px 8px; border-radius: 4px; font-family: monospace; font-weight: bold; margin-right: 10px; letter-spacing: 0.5px; display: inline-block; min-width: 110px; border-left: 3px solid #4A90E2;\">🎟️ Billetterie</span>\n  <a href=\"https://billetteriesiel.minculture.gov.ma/tickets/salon-du-livre/4\" style=\"color: #4A90E2; text-decoration: none; font-weight: 600;\">Achat des billets officiels</a>\n</li>\n</ul>\n</div>\n\n<h2 style=\"color: #4A90E2; border-bottom: 2px solid #4A90E2; padding-bottom: 5px;\">Mots-Clés et Référencement</h2>\n<div style=\"margin-bottom: 30px;\">\n  <div style=\"display: flex; flex-wrap: wrap; gap: 10px; margin-bottom: 20px;\">\n    <strong style=\"display: inline-block; padding: 6px 12px; background-color: #f0f7ff; border-radius: 4px; color: #4A90E2; font-size: 14px; border: 1px solid rgba(74, 144, 226, 0.2);\">Salon du livre Maroc</strong>\n    <strong style=\"display: inline-block; padding: 6px 12px; background-color: #f0f7ff; border-radius: 4px; color: #4A90E2; font-size: 14px; border: 1px solid rgba(74, 144, 226, 0.2);\">SIEL Rabat 2025</strong>\n    <strong style=\"display: inline-block; padding: 6px 12px; background-color: #f0f7ff; border-radius: 4px; color: #4A90E2; font-size: 14px; border: 1px solid rgba(74, 144, 226, 0.2);\">Événement littéraire Maroc</strong>\n    <strong style=\"display: inline-block; padding: 6px 12px; background-color: #f0f7ff; border-radius: 4px; color: #4A90E2; font-size: 14px; border: 1px solid rgba(74, 144, 226, 0.2);\">Salon international édition livre</strong>\n    <strong style=\"display: inline-block; padding: 6px 12px; background-color: #f0f7ff; border-radius: 4px; color: #4A90E2; font-size: 14px; border: 1px solid rgba(74, 144, 226, 0.2);\">Littérature marocaine</strong>\n    <strong style=\"display: inline-block; padding: 6px 12px; background-color: #f0f7ff; border-radius: 4px; color: #4A90E2; font-size: 14px; border: 1px solid rgba(74, 144, 226, 0.2);\">Salon du livre Rabat</strong>\n    <strong style=\"display: inline-block; padding: 6px 12px; background-color: #f0f7ff; border-radius: 4px; color: #4A90E2; font-size: 14px; border: 1px solid rgba(74, 144, 226, 0.2);\">Édition 2025</strong>\n    <strong style=\"display: inline-block; padding: 6px 12px; background-color: #f0f7ff; border-radius: 4px; color: #4A90E2; font-size: 14px; border: 1px solid rgba(74, 144, 226, 0.2);\">Culture marocaine</strong>\n  </div>\n</div>",

    "image": "assets/images/blogs/SIEL-Rabat.png",
    "description": "Découvrez tout ce qu'il faut savoir sur le 30ème Salon International de l'Edition et du Livre (SIEL) de Rabat en 2025, avec des informations pratiques et des liens utiles.",
    "collection": "culture",
    "injectedImages": [
      {
        "src": "assets/images/blogs/injectedBlogsImages/siel-rabat.png",
        "line": 2,
        "position": "center"
      }
    ],
    "dateEcriture": "2025-04-08",
    "redirections": [
      {
        "name": "Site Officiel SIEL",
        "url": "https://siel.ma/fr/accueil/"
      },
      {
        "name": "Billetterie Officielle",
        "url": "https://billetteriesiel.minculture.gov.ma/tickets/salon-du-livre/4"
      }
    ]
},

  "itzenata-gitex": {
    "title": "ITZENATA au GITEX AFRICA 2025 : Une Immersion Stratégique dans l'Écosystème Tech Continental",

    "content": "Le GITEX AFRICA 2025, événement phare de l'innovation technologique sur le continent, a été l'occasion pour ITZENATA de renforcer sa présence dans l'écosystème numérique africain. Notre équipe a parcouru ce carrefour incontournable des technologies émergentes pour tisser des liens stratégiques et s'imprégner des dernières avancées du secteur.\n\n<h2 style=\"color: #258F95; border-bottom: 2px solid #258F95; padding-bottom: 5px;\">Une exploration stratégique des innovations technologiques</h2>\nITZENATA n'a pas seulement participé au GITEX AFRICA 2025 en tant que visiteur passif, mais s'est engagé activement dans une démarche de veille technologique approfondie. Nos équipes ont exploré les différents pavillons thématiques pour identifier les solutions les plus pertinentes pour notre développement futur.\n\nLes secteurs qui ont particulièrement retenu notre attention incluent :\n\n<ul style=\"padding-left: 20px;\">\n<li>Les plateformes d'intelligence artificielle adaptées au contexte africain</li>\n<li>Les infrastructures cloud souveraines en plein essor sur le continent</li>\n<li>Les solutions de cybersécurité spécifiques aux enjeux régionaux</li>\n<li>Les technologies fintech innovantes facilitant l'inclusion financière</li>\n</ul>\n\n<h2 style=\"color: #258F95; border-bottom: 2px solid #258F95; padding-bottom: 5px;\">Des échanges fructueux avec l'écosystème startup</h2>\nL'un des points forts de notre participation a été les nombreux échanges avec les startups les plus innovantes du continent. Ces rencontres nous ont permis d'identifier plusieurs opportunités de collaboration prometteuses :\n\n<ul style=\"padding-left: 20px;\">\n<li><strong style=\"color: #258F95;\">AgriTech Solutions</strong> : Cette startup kenyane développe des solutions d'irrigation intelligente pilotées par IA que nous envisageons d'intégrer dans nos projets de développement durable.</li>\n<li><strong style=\"color: #258F95;\">FinSecure</strong> : Basée à Dakar, cette jeune pousse propose une plateforme de détection des fraudes particulièrement adaptée aux marchés émergents, avec qui nous avons entamé des discussions pour une potentielle intégration.</li>\n<li><strong style=\"color: #258F95;\">EduTech Africa</strong> : Cette startup marocaine développe des outils d'apprentissage personnalisé que nous évaluons pour renforcer nos programmes de formation interne.</li>\n<li><strong style=\"color: #258F95;\">CloudNative Solutions</strong> : Cette équipe rwandaise propose une approche innovante pour l'optimisation des infrastructures cloud, un domaine stratégique pour notre transformation numérique.</li>\n</ul>\n\nCes échanges ne se sont pas limités à de simples présentations commerciales, mais ont donné lieu à des discussions approfondies sur les possibilités d'intégration technique et les modèles de collaboration envisageables.\n\n<h2 style=\"color: #258F95; border-bottom: 2px solid #258F95; padding-bottom: 5px;\">Des rencontres privilégiées avec les leaders technologiques</h2>\nLe GITEX AFRICA a également été l'occasion de dialoguer avec les représentants des plus grandes entreprises technologiques mondiales présentes sur le continent. Parmi nos échanges les plus significatifs :\n\n<ul style=\"padding-left: 20px;\">\n<li><strong style=\"color: #258F95;\">ORACLE</strong> : Nos discussions avec l'équipe d'ORACLE ont porté sur leurs nouvelles solutions cloud adaptées au marché africain. Leur approche hybride, combinant infrastructures locales et services globaux, pourrait constituer un levier important pour notre stratégie d'hébergement de données.</li>\n<li><strong style=\"color: #258F95;\">IBM</strong> : Les représentants d'IBM nous ont présenté leurs solutions d'intelligence artificielle spécifiquement développées pour répondre aux défis africains, avec une attention particulière pour les applications dans les secteurs de la santé et de l'agriculture.</li>\n<li><strong style=\"color: #258F95;\">SAP</strong> : Nos échanges avec l'équipe SAP ont mis en lumière des solutions ERP spécifiquement configurées pour les défis logistiques du continent, un domaine crucial pour l'optimisation de nos opérations.</li>\n<li><strong style=\"color: #258F95;\">Huawei</strong> : Les innovations présentées par Huawei en matière d'infrastructures 5G et de smart cities ont particulièrement retenu notre attention pour nos projets de développement urbain intelligent.</li>\n</ul>\n\n<h2 style=\"color: #258F95; border-bottom: 2px solid #258F95; padding-bottom: 5px;\">Les tendances technologiques qui façonneront l'avenir du continent</h2>\nNotre participation au GITEX AFRICA 2025 nous a permis d'identifier cinq tendances majeures qui structureront l'évolution technologique du continent dans les années à venir :\n\n<ol style=\"padding-left: 20px;\">\n<li><strong style=\"color: #258F95;\">L'émergence d'une IA \"made in Africa\"</strong> : De nombreuses solutions d'intelligence artificielle développées localement et adaptées aux spécificités du continent démontrent une maturité croissante de l'écosystème tech africain.</li>\n<li><strong style=\"color: #258F95;\">La souveraineté numérique comme priorité stratégique</strong> : Les initiatives de cloud souverain et de législations sur la protection des données se multiplient, reflétant une volonté d'autonomie technologique.</li>\n<li><strong style=\"color: #258F95;\">L'accélération des solutions fintech transfrontalières</strong> : L'interopérabilité des systèmes de paiement entre pays africains progresse rapidement, facilitant les échanges commerciaux intra-continentaux.</li>\n<li><strong style=\"color: #258F95;\">Le déploiement de solutions tech à impact social</strong> : Les technologies au service de l'éducation, de la santé et de l'agriculture durable occupent une place croissante dans l'écosystème d'innovation.</li>\n<li><strong style=\"color: #258F95;\">L'intégration du développement durable dans la tech</strong> : Les considérations environnementales sont désormais au cœur de nombreuses solutions technologiques, de la conception des data centers à l'économie circulaire des équipements électroniques.</li>\n</ol>\n\n<h2 style=\"color: #258F95; border-bottom: 2px solid #258F95; padding-bottom: 5px;\">Perspectives et prochaines étapes</h2>\nNotre participation au GITEX AFRICA 2025 ne constitue pas une fin en soi, mais le point de départ d'une stratégie d'engagement renforcé dans l'écosystème technologique africain. Dans les semaines à venir, notre équipe va :\n\n<ul style=\"padding-left: 20px;\">\n<li>Approfondir les discussions avec les startups et entreprises les plus prometteuses rencontrées lors de l'événement</li>\n<li>Lancer une phase d'évaluation technique des solutions identifiées comme potentiellement intégrables à notre stack technologique</li>\n<li>Organiser des sessions de partage de connaissances en interne pour diffuser les apprentissages acquis lors du salon</li>\n<li>Établir une feuille de route pour l'implémentation des innovations les plus pertinentes pour notre développement</li>\n</ul>\n\nLe GITEX AFRICA s'affirme plus que jamais comme un rendez-vous incontournable pour comprendre les dynamiques technologiques qui transforment le continent. Pour ITZENATA, cette participation marque une étape importante dans notre engagement à contribuer activement à la révolution numérique africaine.\n\n<div style=\"margin-top: 30px;\">\n  <h3 style=\"color: #258F95; font-size: 20px; margin-bottom: 15px;\">Tags</h3>\n  \n  <div style=\"display: flex; flex-wrap: wrap; gap: 10px; margin-bottom: 20px;\">\n    <strong style=\"display: inline-block; padding: 6px 12px; background-color: #f0f5f5; border-radius: 4px; color: #258F95; font-size: 14px; border: 1px solid rgba(37, 143, 149, 0.2);\">GITEX Africa</strong>\n    <strong style=\"display: inline-block; padding: 6px 12px; background-color: #f0f5f5; border-radius: 4px; color: #258F95; font-size: 14px; border: 1px solid rgba(37, 143, 149, 0.2);\">ITZENATA</strong>\n    <strong style=\"display: inline-block; padding: 6px 12px; background-color: #f0f5f5; border-radius: 4px; color: #258F95; font-size: 14px; border: 1px solid rgba(37, 143, 149, 0.2);\">Innovation africaine</strong>\n    <strong style=\"display: inline-block; padding: 6px 12px; background-color: #f0f5f5; border-radius: 4px; color: #258F95; font-size: 14px; border: 1px solid rgba(37, 143, 149, 0.2);\">Tech Maroc</strong>\n    <strong style=\"display: inline-block; padding: 6px 12px; background-color: #f0f5f5; border-radius: 4px; color: #258F95; font-size: 14px; border: 1px solid rgba(37, 143, 149, 0.2);\">Startups africaines</strong>\n    <strong style=\"display: inline-block; padding: 6px 12px; background-color: #f0f5f5; border-radius: 4px; color: #258F95; font-size: 14px; border: 1px solid rgba(37, 143, 149, 0.2);\">Oracle Afrique</strong>\n    <strong style=\"display: inline-block; padding: 6px 12px; background-color: #f0f5f5; border-radius: 4px; color: #258F95; font-size: 14px; border: 1px solid rgba(37, 143, 149, 0.2);\">Transformation digitale</strong>\n    <strong style=\"display: inline-block; padding: 6px 12px; background-color: #f0f5f5; border-radius: 4px; color: #258F95; font-size: 14px; border: 1px solid rgba(37, 143, 149, 0.2);\">Cloud souverain</strong>\n    <strong style=\"display: inline-block; padding: 6px 12px; background-color: #f0f5f5; border-radius: 4px; color: #258F95; font-size: 14px; border: 1px solid rgba(37, 143, 149, 0.2);\">IA Afrique</strong>\n    <strong style=\"display: inline-block; padding: 6px 12px; background-color: #f0f5f5; border-radius: 4px; color: #258F95; font-size: 14px; border: 1px solid rgba(37, 143, 149, 0.2);\">Fintech africaine</strong>\n    <strong style=\"display: inline-block; padding: 6px 12px; background-color: #f0f5f5; border-radius: 4px; color: #258F95; font-size: 14px; border: 1px solid rgba(37, 143, 149, 0.2);\">Écosystème numérique africain</strong>\n    <strong style=\"display: inline-block; padding: 6px 12px; background-color: #f0f5f5; border-radius: 4px; color: #258F95; font-size: 14px; border: 1px solid rgba(37, 143, 149, 0.2);\">Salon technologique Marrakech</strong>\n    <strong style=\"display: inline-block; padding: 6px 12px; background-color: #f0f5f5; border-radius: 4px; color: #258F95; font-size: 14px; border: 1px solid rgba(37, 143, 149, 0.2);\">Événement tech 2025</strong>\n  </div>\n</div>",

    "image": "assets/images/blogs/itzenataGitexX.png",
    "description": "Découvrez comment ITZENATA a exploré les innovations technologiques africaines lors du GITEX AFRICA 2025, établissant des partenariats stratégiques avec startups et grandes entreprises pour accélérer sa transformation numérique.",
    "collection": "technologie",
    "injectedImages": [
      {
        "src": "assets/images/blogs/injectedBlogsImages/itzenataGitex1.png",
        "line": 6,
        "position": "right"
      },
      {
        "src": "assets/images/blogs/injectedBlogsImages/itzenataGitex.png",
        "line": 18,
        "position": "right"
      }
    ],
    "dateEcriture": "2025-04-21"
  },

  "ui-ux": {
    "title": "L’Essentiel du Design UI/UX : Principes, Avantages et Défis",
    "content": "Le design UI/UX est au cœur de la création d’applications web et mobiles, déterminant comment les utilisateurs interagissent avec les interfaces et vivent l’expérience numérique. Comprendre les principes de base, les avantages et les défis du design UI/UX est essentiel pour créer des produits qui captivent et satisfont les utilisateurs.\n\n Principes du Design UI/UX\n\n1. Utilisabilité :\n   Le design UI/UX vise à rendre les interfaces faciles à utiliser. Cela implique une navigation intuitive, des éléments interactifs clairs et une logique cohérente dans l’organisation de l’information.\n\n2. Esthétique :\n   Un design visuellement attrayant améliore l’expérience utilisateur. L’utilisation de couleurs harmonieuses, de typographies lisibles et d’éléments graphiques bien conçus contribue à une présentation agréable et professionnelle.\n\n3. Accessibilité :\n   Concevoir pour l'accessibilité garantit que les interfaces sont utilisables par tous, y compris les personnes ayant des handicaps. Cela comprend des pratiques telles que la conception de contrastes suffisants, l'utilisation de textes alternatifs pour les images et des fonctionnalités de navigation clavier.\n\n4. Réactivité :\n   Les interfaces doivent être réactives, c’est-à-dire qu'elles doivent s’adapter à différents dispositifs et tailles d’écran. Un design réactif assure une expérience cohérente, que ce soit sur un ordinateur de bureau, une tablette ou un smartphone.\n\n Avantages du Design UI/UX\n\n1. Amélioration de l’Engagement Utilisateur :\n   Un design bien pensé retient les utilisateurs et les encourage à interagir davantage avec l’application. Une expérience utilisateur fluide et plaisante favorise la fidélisation des utilisateurs.\n\n2. Augmentation de la Conversion :\n   Un bon design UI/UX peut augmenter les taux de conversion en guidant les utilisateurs efficacement vers des actions souhaitées, comme l’achat d’un produit ou l’inscription à un service.\n\n3. Réduction des Coûts :\n   Investir dans le design UI/UX dès le début du projet peut réduire les coûts à long terme en minimisant les besoins de modifications majeures et en évitant les problèmes d’utilisation qui nécessitent des corrections coûteuses.\n\n4. Renforcement de la Marque :\n   Un design cohérent et de haute qualité renforce l’image de marque et crée une impression positive auprès des utilisateurs. Cela contribue à la réputation et à la reconnaissance de la marque.\n\n Défis du Design UI/UX\n\n1. Évolution des Besoins Utilisateurs :\n   Les besoins et attentes des utilisateurs évoluent constamment. Les designers doivent rester à jour avec les tendances et les attentes pour offrir des expériences pertinentes et modernes.\n\n2. Complexité de la Conception Réactive :\n   Concevoir pour une multitude de dispositifs et de tailles d’écran peut être complexe. Les designers doivent s’assurer que l’interface fonctionne de manière optimale sur tous les supports.\n\n3. Gestion des Contraintes Techniques :\n   Les contraintes techniques peuvent limiter certaines options de design. Les designers doivent travailler en étroite collaboration avec les développeurs pour trouver des solutions créatives et fonctionnelles.\n\n4. Testing et Validation :\n   Le processus de test est crucial pour s’assurer que le design répond aux besoins des utilisateurs. Cela nécessite des tests continus et des retours d’expérience pour ajuster et améliorer l’interface.\n\nEn conclusion, le design UI/UX est fondamental pour créer des expériences utilisateur exceptionnelles. En respectant les principes clés, en exploitant les avantages et en abordant les défis de manière proactive, les designers peuvent développer des interfaces qui captivent les utilisateurs et répondent à leurs attentes.",
    "image": "assets/images/blogs/ui-ux.avif",
    "description": "",
    "collection": "design",
    "injectedImages": [
      {
        "src": "assets/images/blogs/injectedBlogsImages/uiux.avif",
        "line": 4,
        "position": "right"
      }
    ],
    "dateEcriture": "2024-09-10"
  },

  "Michel Barnier": {
    "title": "Michel Barnier : Un Visionnaire Européen avec un Regard sur le Maroc",
    "content": "Michel Barnier, figure emblématique de la politique européenne, est reconnu pour son rôle influent dans la construction et la gestion de l'Union Européenne. Avec une carrière marquée par des contributions significatives au sein de la Commission Européenne et en tant que négociateur en chef du Brexit, Barnier a démontré une vision stratégique et un engagement envers l'unité européenne.\n\n Une Carrière au Service de l’Europe\n\nBarnier a occupé divers postes clés, notamment celui de Commissaire européen au Marché intérieur et aux Services financiers, où il a joué un rôle crucial dans la réforme des régulations financières de l'UE. Sa gestion des négociations complexes du Brexit a consolidé sa réputation de négociateur rigoureux et compétent.\n\n Un Regard sur le Maroc\n\nOutre ses contributions au niveau européen, Michel Barnier s'intéresse également aux relations entre l'Europe et les pays voisins. Le Maroc, en tant que partenaire stratégique de l'Union Européenne en Afrique du Nord, est un point d'intérêt important pour Barnier. Il voit dans la coopération avec le Maroc un potentiel de développement mutuel et de renforcement des liens économiques et politiques.\n\nBarnier plaide pour une approche équilibrée qui favorise la collaboration tout en respectant les spécificités régionales. Il souligne l'importance de soutenir les initiatives de développement durable au Maroc, ainsi que d'encourager les échanges commerciaux et les investissements qui bénéficient aux deux parties.\n\n Vision pour l’Avenir\n\nAvec une approche pragmatique et un esprit visionnaire, Michel Barnier continue d'influencer les discussions sur la coopération entre l'Europe et le Maroc. Sa vision est celle d'une Europe ouverte et engagée, prête à renforcer ses relations avec ses voisins pour un avenir de prospérité partagée.\n\nEn conclusion, Michel Barnier incarne un leadership européen réfléchi, capable d’intégrer des perspectives globales tout en mettant en avant des priorités locales et régionales. Son engagement envers le renforcement des relations avec le Maroc témoigne de sa volonté de promouvoir une coopération internationale constructive et bénéfique pour tous.",
    "image": "assets/images/blogs/MichelBanier.avif",
    "description": "",
    "collection": "politics",
    "injectedImages": [
      {
        "src": "assets/images/blogs/injectedBlogsImages/MichelBarnier2.avif",
        "line": 4,
        "position": "right"
      }
    ],
    "dateEcriture": "2024-09-10"
  },

  "siteweb2025": {
    "title": "Les Meilleurs Sites Web de 2025 : Tendances et Innovations",
    "content": " Les Meilleurs Sites Web de 2025 : Tendances et Innovations\n\nL’année 2025 promet de révolutionner notre expérience en ligne avec une série de sites web innovants et captivants. Alors que les technologies évoluent à un rythme rapide, certains sites se démarquent par leur design avant-gardiste, leurs fonctionnalités uniques et leur capacité à offrir une expérience utilisateur exceptionnelle. Voici une sélection des meilleurs sites web à surveiller cette année :\n\n1. VortexUI\nURL : [vortexui.com](https://www.vortexui.com)\n\nVortexUI redéfinit le design web avec une interface utilisateur totalement immersive grâce à la réalité augmentée (RA). Ce site utilise des éléments interactifs en 3D qui permettent aux utilisateurs de naviguer à travers des environnements virtuels. La personnalisation de l'expérience utilisateur est poussée à un nouveau niveau avec des animations réactives et des interactions basées sur l'IA.\n\n2. EcoFuture\nURL : [ecofuture.org](https://www.ecofuture.org)\n\nEcoFuture se distingue par son engagement envers la durabilité et l'éducation environnementale. Avec une interface élégante et épurée, le site propose des visualisations de données interactives sur les tendances écologiques mondiales. Les utilisateurs peuvent explorer des simulations de l'impact de leurs choix de consommation et découvrir des initiatives locales pour un avenir plus vert.\n\n3. Artistry\nURL : [artistry.com](https://www.artistry.com)\n\nArtistry est un site de galeries d'art en ligne qui exploite les dernières technologies d’IA pour personnaliser l'expérience de découverte artistique. Les visiteurs peuvent explorer des œuvres d’art en fonction de leurs préférences et de leur humeur, grâce à un algorithme intelligent qui recommande des pièces en temps réel. Le site offre également des visites virtuelles guidées par des experts.\n\n4. BoilTheFrog\nURL : [boilthefrog.com](https://www.boilthefrog.com)\n\nBoilTheFrog propose un concept original et unique : il permet aux utilisateurs de créer des transitions musicales fluides entre deux artistes complètement différents. En connectant intelligemment les genres musicaux, le site tisse un chemin musical qui amène les utilisateurs à découvrir de nouveaux artistes tout en restant dans leur zone de confort. Idéal pour les mélomanes en quête de nouvelles expériences sonores.\n\n5. Bruno Simon\nURL : [bruno-simon.com](https://www.bruno-simon.com)\n\nBruno Simon est un portfolio interactif révolutionnaire qui se démarque par son approche ludique de la navigation. Son site, qui permet aux utilisateurs de piloter une voiture miniature à travers les différents projets qu'il présente, est un véritable modèle de créativité en matière de web design. En 2025, Bruno Simon continue d'impressionner avec des mises à jour constantes et des expériences utilisateurs innovantes.",
    "image": "assets/images/blogs/TopWeb.avif",
    "description": "",
    "collection": "autres",
    "injectedImages": [
      {
        "src": "assets/images/blogs/injectedBlogsImages/voretxUI.avif",
        "line": 3,
        "position": "right"
      },
      {
        "src": "assets/images/blogs/injectedBlogsImages/EcoFuture.avif",
        "line": 9,
        "position": "left"
      },
      {
        "src": "assets/images/blogs/injectedBlogsImages/Amway.avif",
        "line": 16,
        "position": "right"
      },
      {
        "src": "assets/images/blogs/injectedBlogsImages/BoilToFrog.avif",
        "line": 20,
        "position": "right"
      },
      {
        "src": "assets/images/blogs/injectedBlogsImages/brunoPort.avif",
        "line": 25,
        "position": "right"
      }
    ],
    "dateEcriture": "2024-09-10"
  },

  "sitewebMaroc": {
    "title": "Création de Sites Web au Maroc : Croissance et Opportunités",
    "content": "Création de Sites Web au Maroc : Croissance et Opportunités\n\nAu Maroc, la création de sites web connaît une croissance exponentielle. Avec l'évolution rapide des technologies numériques, de plus en plus d'entreprises, d'entrepreneurs et de particuliers se tournent vers le digital pour renforcer leur présence en ligne. Cet article explore les raisons derrière cette expansion, les avantages qu'offre le marché marocain et les opportunités pour les créateurs de sites web.\n\n1. L'Écosystème Numérique au Maroc\n\nLe Maroc se positionne de plus en plus comme un hub technologique en Afrique. Des infrastructures en amélioration, une population jeune et connectée, ainsi qu'une volonté gouvernementale de promouvoir la transformation digitale, favorisent l'émergence de start-ups et de développeurs web. Les entreprises marocaines réalisent que la présence en ligne est essentielle pour rester compétitives, que ce soit à travers des sites vitrine ou des plateformes de vente en ligne.\n\n 2. Pourquoi Créer un Site Web au Maroc ?\n\n1. Visibilité Accrue\nAujourd'hui, avoir une vitrine en ligne est essentiel pour les entreprises. Un site web permet non seulement d'augmenter la visibilité, mais aussi de toucher une clientèle internationale. Grâce aux outils de référencement (SEO), les entreprises peuvent optimiser leur site pour attirer plus de visiteurs et se démarquer de la concurrence.\n\n2. Accessibilité 24/7\nContrairement aux magasins physiques, un site web est accessible à toute heure. Les clients potentiels peuvent consulter des produits, obtenir des informations, ou même effectuer des achats sans les contraintes des horaires d'ouverture.\n\n3. Crédibilité\nDans un monde où la première impression compte énormément, un site web bien conçu inspire confiance. Pour une petite entreprise, un site professionnel est un levier de crédibilité face aux clients et aux partenaires.\n\n3. Les Technologies Utilisées\n\nLa création de sites web au Maroc suit les tendances mondiales. Les développeurs marocains utilisent des outils variés tels que WordPress, Shopify, Prestashop pour la gestion de contenu et le commerce en ligne. Pour les projets plus personnalisés, des frameworks comme React.js, Vue.js et Laravel sont populaires. Le design et l’expérience utilisateur sont également au centre des préoccupations, avec une attention particulière sur la responsivité, garantissant ainsi une navigation fluide sur mobile, tablette et ordinateur.\n\n4. L'Avenir de la Création Web au Maroc\n\nL'avenir de la création de sites web au Maroc s'annonce prometteur. Avec l'augmentation des investissements dans les infrastructures numériques, l'accès généralisé à internet et une demande croissante des entreprises pour une présence en ligne, les créateurs de sites web ont un rôle clé à jouer dans cette transformation. De plus, le développement du commerce électronique et l'intérêt accru pour les solutions innovantes comme les applications web progressives (PWA) et le cloud computing offrent des perspectives de croissance continue.",
    "image": "assets/images/blogs/creationSiteMaroc.avif",
    "description": "",
    "collection": "dev",
    "injectedImages": [
      {
        "src": "assets/images/blogs/injectedBlogsImages/website.avif",
        "line": 3,
        "position": "right"
      }
    ],
    "dateEcriture": "2024-09-10"
  },

  "sitewebAdminstartion": {
    "title": "Comment une Bonne Administration d'un Site Web ou d'une Application Aide la Société à Avancer",
    "content": "Comment une Bonne Administration d'un Site Web ou d'une Application Aide la Société à Avancer\n\nÀ l'ère numérique, les sites web, les plateformes et les applications jouent un rôle crucial dans notre vie quotidienne. De l'éducation à la santé, en passant par le commerce et la communication, ces outils numériques influencent presque tous les aspects de notre société. Cependant, la réussite d'un site web ou d'une application ne dépend pas seulement de sa conception ou de sa fonctionnalité initiale. Une administration efficace est essentielle pour maximiser son impact et contribuer positivement à la société. Voici comment une bonne administration aide à faire avancer la société.\n\n1. Optimisation des Ressources \n\nUne bonne administration permet d'optimiser l'utilisation des ressources, qu'il s'agisse de serveurs, de bande passante ou de personnel. En surveillant en permanence les performances et en ajustant les ressources en fonction des besoins, les administrateurs garantissent une expérience utilisateur fluide et sans interruption. Cela se traduit par une meilleure accessibilité des services en ligne, réduisant les temps d'attente et augmentant la satisfaction des utilisateurs.\n\n2. Sécurité Renforcée\n\nLa sécurité est un aspect crucial de l'administration de tout site web ou application. En mettant en œuvre des mesures de sécurité robustes, telles que la gestion des accès, le cryptage des données et les mises à jour régulières, les administrateurs protègent les informations sensibles des utilisateurs contre les cyberattaques. Une gestion sécurisée des données renforce la confiance des utilisateurs et protège la réputation de la plateforme, ce qui est essentiel pour maintenir une société numérique fiable et sûre.\n\n3. Amélioration Continue\n\nUne administration efficace ne se contente pas de maintenir le statu quo. Elle implique également une évaluation continue des performances et une amélioration constante des fonctionnalités. Les administrateurs recueillent des retours d'expérience, analysent les données d'utilisation et identifient les domaines à améliorer. Cette approche proactive permet de répondre aux besoins changeants des utilisateurs et d'intégrer des innovations qui peuvent transformer les services en ligne en outils encore plus puissants pour la société.\n\n4. Accessibilité et Inclusion\n\nUne administration réussie veille à ce que les sites web et les applications soient accessibles à tous les utilisateurs, y compris ceux ayant des besoins spécifiques. En mettant en œuvre des normes d'accessibilité, telles que les directives WCAG (Web Content Accessibility Guidelines), les administrateurs garantissent que les plateformes sont utilisables par un public diversifié. Cela contribue à l'inclusion numérique et assure que personne n'est laissé pour compte dans l'accès aux informations et aux services en ligne.\n\n5. Efficacité Opérationnelle\n\nUne bonne administration optimise également les processus opérationnels en automatisant les tâches répétitives et en utilisant des outils de gestion performants. Cela permet de réduire les erreurs humaines, d'accélérer les processus et d'améliorer l'efficacité globale. Par exemple, l'automatisation des mises à jour et des sauvegardes garantit que les systèmes restent à jour et sécurisés sans nécessiter une surveillance constante.\n\n6. Support et Assistance\n\nUn autre aspect important de l'administration est la ourniture d'un support efficace aux utilisateurs. En mettant en place des systèmes de support client réactifs, tels que des forums, des chats en direct ou des centres d'appel, les administrateurs aident les utilisateurs à résoudre leurs problèmes rapidement et efficacement. Un bon support contribue à une expérience utilisateur positive et favorise une adoption plus large des technologies, ce qui est bénéfique pour la société dans son ensemble.\n\nConclusion\n\nLa bonne administration d'un site web, d'une plateforme ou d'une application est essentielle pour leur succès et leur impact positif sur la société. En optimisant les ressources, en renforçant la sécurité, en améliorant continuellement les fonctionnalités, en garantissant l'accessibilité, en augmentant l'efficacité opérationnelle et en fournissant un support de qualité, les administrateurs jouent un rôle clé dans le progrès numérique. Une gestion efficace permet non seulement d'améliorer les services en ligne, mais aussi de contribuer au développement d'une société plus connectée, sécurisée et inclusive.",
    "image": "assets/images/blogs/AdminWebMaroc.avif",
    "description": "",
    "collection": "dev",
    "injectedImages": [
      {
        "src": "assets/images/blogs/injectedBlogsImages/admin.avif",
        "line": 3,
        "position": "right"
      }
    ],
    "dateEcriture": "2024-09-10"
  },
  "applicationMobileEntreprise": {
    "title": "Les Applications Mobiles pour les Entreprises : Grands et Petits Bénéfices",
    "content": "Les Applications Mobiles pour les Entreprises : Grands et Petits Bénéfices\n\nDans un monde où la technologie évolue rapidement, les entreprises, qu'elles soient grandes ou petites, se tournent de plus en plus vers les applications mobiles pour améliorer leur compétitivité. Cet article explore les avantages des applications mobiles pour les entreprises de différentes tailles et pourquoi elles sont devenues indispensables dans la gestion et la croissance des entreprises modernes.\n\n1. Accessibilité Accrue pour les Clients\n\nL'un des principaux avantages d'une application mobile pour une entreprise est la capacité d'offrir une accessibilité continue. Les clients peuvent interagir avec la marque ou le service où qu'ils soient, et à tout moment. Pour les grandes entreprises, cela permet une présence mondiale avec une disponibilité 24/7, tandis que pour les petites entreprises, c'est l'occasion de toucher de nouveaux marchés et d'améliorer leur visibilité.\n\n2. Amélioration de l’Expérience Utilisateur\n\nLes applications mobiles permettent d’offrir une expérience utilisateur fluide et personnalisée. Elles aident les entreprises à simplifier le parcours client, améliorant ainsi la satisfaction et la fidélisation des clients. Les grandes entreprises utilisent des technologies telles que l’intelligence artificielle pour rendre l’expérience plus engageante, tandis que les petites entreprises peuvent créer une relation plus intime avec leur clientèle.\n\n3. Marketing Direct et Engagement Renforcé\n\nLes applications offrent des outils comme les notifications push, les offres exclusives, et les programmes de fidélité, ce qui permet aux entreprises d'engager les clients directement sur leurs appareils mobiles. Les grandes entreprises peuvent ainsi promouvoir de nouveaux produits à grande échelle, tandis que les petites entreprises peuvent personnaliser leurs offres pour fidéliser leurs clients et stimuler les ventes.\n\n4. Optimisation des Opérations Internes\n\nLes applications ne servent pas seulement à interagir avec les clients, elles peuvent également améliorer les processus internes. Les grandes entreprises les utilisent pour gérer les équipes, la logistique, et la communication interne. Quant aux petites entreprises, elles peuvent automatiser des tâches comme la gestion des commandes ou la planification, réduisant ainsi les coûts et améliorant l'efficacité.\n\n5. Connaissance Profonde des Clients\n\nGrâce aux données collectées par les applications mobiles, les entreprises peuvent obtenir des informations précieuses sur les comportements et préférences de leurs utilisateurs. Les grandes entreprises utilisent ces données pour affiner leurs campagnes marketing, tandis que les petites entreprises peuvent mieux comprendre leurs clients et ajuster leurs offres en conséquence.\n\n6. Renforcement de la Fidélité à la Marque\n\nUne application mobile bien conçue devient une extension de la marque. Pour les grandes entreprises, elle contribue à renforcer la confiance des consommateurs à l'échelle mondiale. Pour les petites entreprises, elle permet de paraître plus professionnelle et innovante, augmentant ainsi leur crédibilité.\n\n7. Réduction des Coûts à Long Terme\n\nBien que le développement d'une application mobile demande un investissement initial, elle peut s'avérer très rentable à long terme en réduisant les coûts liés à l’automatisation des processus, à la communication, et à la gestion des ventes.\n\nConclusion\n\nQu'il s'agisse d'une grande ou d'une petite entreprise, les applications mobiles offrent des bénéfices considérables. Elles augmentent l'accessibilité, optimisent l'expérience utilisateur, et renforcent la présence et la crédibilité de la marque. Les entreprises de toutes tailles peuvent tirer parti des applications mobiles pour gagner en compétitivité et en efficacité sur le long terme.",
    "image": "assets/images/blogs/AppWeb.avif",
    "description": "",
    "collection": "dev",
    "injectedImages": [
      {
        "src": "assets/images/blogs/injectedBlogsImages/app.avif",
        "line": 3,
        "position": "right"
      }
    ],
    "dateEcriture": "2024-09-11"
  },

  "seisme": {
    "title": "Séisme de 5.2 à Taza : Comprendre les causes et les moyens de protection",
    "content": "Un tremblement de terre de magnitude 5.2 a frappé la région de Taza, rappelant tragiquement la vulnérabilité sismique du Maroc. Cet événement évoque immédiatement le séisme dévastateur d’Al Haouz en 2023, qui a causé des milliers de victimes. Comprendre les causes des séismes et adopter des mesures de prévention est essentiel pour limiter les dégâts et sauver des vies.\n\nCauses des tremblements de terre\n\nLes séismes sont provoqués par le mouvement des plaques tectoniques. Le Maroc se trouve à la jonction entre la plaque africaine et la plaque eurasienne, rendant certaines régions plus sujettes aux secousses sismiques. L’accumulation d’énergie dans la croûte terrestre finit par être libérée sous forme d’ondes sismiques, entraînant des secousses plus ou moins violentes.\n\nLien avec le séisme d’Al Haouz\n\nLe tremblement de terre de Taza rappelle celui d’Al Haouz par son intensité et son impact sur la population. Si les dommages ont été moindres, il souligne néanmoins l’urgence de renforcer les infrastructures et d’adopter des stratégies de prévention adaptées.\n\nComment se protéger contre un tremblement de terre ?\n\n1. Construire selon des normes parasismiques\n   - Utiliser des matériaux résistants aux secousses.\n   Renforcer les structures existantes.\n    Sensibiliser les populations aux bonnes pratiques de construction.\n\n2. Préparer un plan d’urgence\n    Identifier les zones sûres dans les bâtiments.\n    Prévoir un kit de survie (eau, nourriture, lampe torche, radio).\n    Organiser des exercices d’évacuation.\n\n3. Réagir efficacement lors d’un séisme\n    Se protéger sous une table ou près d’un mur porteur.\n   - Éviter les ascenseurs et les escaliers.\n    Après la secousse, couper l’électricité et le gaz si possible.\n\n4. Développer des systèmes d’alerte et de surveillance\n    Installer des capteurs pour détecter les secousses à l’avance.\n   Mettre en place un système d’alerte rapide.\n\nVers une meilleure résilience\n\nFace à la menace sismique, il est crucial d’améliorer les infrastructures et de sensibiliser les populations. La prévention reste la meilleure arme contre les catastrophes naturelles. Le séisme de Taza nous rappelle que nous devons agir dès maintenant pour limiter les risques futurs.\n",
    "image": "assets/images/blogs/TremblementDeTerre.avif",
    "description": "Un séisme de magnitude 5.2 a frappé Taza, soulignant la nécessité de renforcer la prévention et la résilience face aux tremblements de terre.",
    "collection": "autres",
    "injectedImages": [
      {
        "src": "assets/images/blogs/injectedBlogsImages/seisme1.avif",
        "line": 4,
        "position": "right"
      },
      {
        "src": "assets/images/blogs/injectedBlogsImages/seisme2.avif",
        "line": 19,
        "position": "right"
      }
    ],
    "dateEcriture": "2025-02-13"
  }
}
